audmath/__init__.py
audmath/core/__init__.py
audmath/core/api.py
audmath/core/conftest.py
audmath/core/utils.py
audmath-1.4.3.dist-info/licenses/LICENSE
docs/changelog.rst
docs/conf.py
docs/contributing.rst
docs/genindex.rst
docs/index.rst
docs/installation.rst
docs/usage.rst
docs/_templates/autosummary/base.rst
docs/_templates/autosummary/class.rst
docs/_templates/autosummary/function.rst
docs/api-src/audmath.rst
misc/benchmark.py
tests/test_db.py
tests/test_duration_in_seconds.py
tests/test_inverse_db.py
tests/test_inverse_normal_distribution.py
tests/test_rms.py
tests/test_samples.py
tests/test_similarity.py
tests/test_window.py
audmath-1.4.3.dist-info/METADATA
audmath-1.4.3.dist-info/WHEEL
audmath-1.4.3.dist-info/top_level.txt
audmath-1.4.3.dist-info/RECORD
