Metadata-Version: 2.4
Name: audmath
Version: 1.4.3
Summary: Math function implemented using numpy
Author-email: Hagen Wierstorf <hwierstorf@audeering.com>
License-Expression: MIT
Project-URL: repository, https://github.com/audeering/audmath/
Project-URL: documentation, https://audeering.github.io/audmath/
Keywords: Python,tools,math
Classifier: Development Status :: 5 - Production/Stable
Classifier: Intended Audience :: Science/Research
Classifier: Intended Audience :: Developers
Classifier: Operating System :: OS Independent
Classifier: Programming Language :: Python
Classifier: Programming Language :: Python :: 3
Classifier: Programming Language :: Python :: 3.10
Classifier: Programming Language :: Python :: 3.11
Classifier: Programming Language :: Python :: 3.12
Classifier: Programming Language :: Python :: 3.13
Classifier: Programming Language :: Python :: 3.14
Classifier: Topic :: Scientific/Engineering
License-File: LICENSE
Requires-Dist: numpy
Dynamic: license-file
